qtoggleserver/rpigpio/__init__.py
qtoggleserver/rpigpio/rpigpio.py
qtoggleserver/rpigpio/rpigpiofloat.py
qtoggleserver_rpigpio-1.3.0.dist-info/licenses/LICENSE.txt
qtoggleserver_rpigpio-1.3.0.dist-info/METADATA
qtoggleserver_rpigpio-1.3.0.dist-info/WHEEL
qtoggleserver_rpigpio-1.3.0.dist-info/top_level.txt
qtoggleserver_rpigpio-1.3.0.dist-info/RECORD
