Metadata-Version: 2.4
Name: qtoggleserver-rpigpio
Version: 1.3.0
Summary: qToggleServer driver for Raspberry Pi GPIOs based on RPi.GPIO
Author-email: Calin Crisan <ccrisan@gmail.com>
License: Apache 2.0
Requires-Python: >=3.11
License-File: LICENSE.txt
Requires-Dist: RPi.GPIO
Dynamic: license-file
